{"stat.walkOneCm":30094,"achievement.openInventory":2,"stat.craftItem.minecraft.planks":24,"stat.leaveGame":2,"stat.useItem.minecraft.log":2,"stat.damageTaken":450,"stat.craftItem.minecraft.crafting_table":1,"stat.mineBlock.minecraft.double_plant":1,"stat.mobKills":3,"stat.craftItem.minecraft.wooden_sword":1,"stat.mineBlock.minecraft.log":8,"stat.useItem.minecraft.porkchop":6,"stat.flyOneCm":30909,"stat.deaths":1,"stat.jump":174,"stat.mineBlock.minecraft.leaves":1,"stat.swimOneCm":2236,"stat.playOneMinute":7678,"stat.fallOneCm":4088,"stat.useItem.minecraft.wooden_sword":9,"stat.entityKilledBy.Zombie":1,"stat.useItem.minecraft.planks":3,"stat.climbOneCm":248,"stat.damageDealt":575,"stat.crouchOneCm":588,"stat.timeSinceDeath":3712,"stat.sprintOneCm":15690,"stat.useItem.minecraft.crafting_table":1,"stat.killEntity.Pig":3,"achievement.exploreAllBiomes":{"value":0,"progress":["ForestHills","River","Plains","Swampland","Savanna"]},"stat.mineBlock.minecraft.tallgrass":2,"stat.diveOneCm":2262,"stat.craftItem.minecraft.stick":4,"stat.craftingTableInteraction":2}